Metadata-Version: 1.0
Name: learnlib
Version: 1.0.0
Summary: For python beginners to learn python programming.
Home-page: http://github.com/LinguaTechnica/learnlib
Author: K Hudson
Author-email: dev@divethree.com
License: MIT
Platform: UNKNOWN
